README.md
setup.py
secret_storage/__init__.py
secret_storage.egg-info/PKG-INFO
secret_storage.egg-info/SOURCES.txt
secret_storage.egg-info/dependency_links.txt
secret_storage.egg-info/requires.txt
secret_storage.egg-info/top_level.txt
secret_storage/storage/LocalStorage.py
secret_storage/storage/S3Storage.py
secret_storage/storage/StorageStrategy.py
secret_storage/storage/__init__.py