Metadata-Version: 1.1
Name: secret-storage
Version: 0.0.2
Summary: Tools for extract sensitive configuration out of your project
Home-page: https://github.com/davidNHK/secret-storage
Author: David Ng
Author-email: david.ng.dev@gmail.com
License: BSD
Download-URL: https://github.com/davidNHK/secret-storage/archive/0.0.2.zip
Keywords: generic-storage,secret-data
Platform: UNKNOWN
